flickr_pkg/__init__.py
flickr_pkg/__main__.py
flickr_pkg/flickr.py
flickr_pkg/language_json.py
flickr_minh_quoc-1.0.1.dist-info/METADATA
flickr_minh_quoc-1.0.1.dist-info/WHEEL
flickr_minh_quoc-1.0.1.dist-info/entry_points.txt
flickr_minh_quoc-1.0.1.dist-info/top_level.txt
flickr_minh_quoc-1.0.1.dist-info/RECORD
