Metadata-Version: 2.1
Name: flickr-minh-quoc
Version: 1.0.1
Summary: A useful tool to mirror flickr photo
Home-page: https://github.com/intek-training-jsc/flickr-mirroring-nvqMinh29101992/
Author: Minh Quoc
Author-email: minh.nong@f4.intek.edu.vn
License: UNKNOWN
Platform: UNKNOWN
Classifier: Programming Language :: Python :: 3
Classifier: License :: OSI Approved :: MIT License
Classifier: Operating System :: OS Independent
Requires-Python: >=3.6
Requires-Dist: certifi (==2020.4.5.1)
Requires-Dist: chardet (==3.0.4)
Requires-Dist: idna (==2.9)
Requires-Dist: langdetect (==1.0.8)
Requires-Dist: requests (==2.23.0)
Requires-Dist: six (==1.14.0)
Requires-Dist: urllib3 (==1.25.9)
